{
    "type": "create:sequenced_assembly",
    "ingredient": {
      "item": "create:brass_casing"
    },
    "loops": 1,
    "results": [
      {
        "item": "kubejs:casing.smart",
        "count": 1
      }
    ],
    "sequence": [
      {
        "type": "create:deploying",
        "ingredients": [
          {
            "item": "kubejs:casing.smart.inc"
          },
          {
            "item": "create:electron_tube"
          }
        ],
        "results": [
          {
            "item": "kubejs:casing.smart.inc"
          }
        ]
      },
      {
        "type": "create:deploying",
        "ingredients": [
          {
            "item": "kubejs:casing.smart.inc"
          },
          {
            "item": "kubejs:comp.cpu.scalar"
          }
        ],
        "results": [
          {
            "item": "kubejs:casing.smart.inc"
          }
        ]
      },
      {
        "type": "create:deploying",
        "ingredients": [
          {
            "item": "kubejs:casing.smart.inc"
          },
          {
            "item": "create:precision_mechanism"
          }
        ],
        "results": [
          {
            "item": "kubejs:casing.smart.inc"
          }
        ]
      }
    ],
    "transitionalItem": {
      "item": "kubejs:casing.smart.inc"
    }
  }