{
  "type": "create:sequenced_assembly",
  "ingredient": {
    "item": "kubejs:advanced_pneumatic_shell"
  },
  "transitionalItem": {
    "item": "kubejs:adv_pneumatic_machine_frame_incomplete"
  },
  "sequence": [
    {
      "type": "create:deploying",
      "ingredients": [
        {
          "item": "kubejs:adv_pneumatic_machine_frame_incomplete"
        },
        {
          "item": "pneumaticcraft:pneumatic_cylinder"
        }
      ],
      "results": [
        {
          "item": "kubejs:adv_pneumatic_machine_frame_incomplete"
        }
      ]
    },
     {
      "type": "create:cutting",
      "ingredients": [
        {
          "item": "kubejs:adv_pneumatic_machine_frame_incomplete"
        }
      ],
      "results": [
        {
          "item": "kubejs:adv_pneumatic_machine_frame_incomplete"
        }
      ]
    },
    {
      "type": "create:deploying",
      "ingredients": [
        {
          "item": "kubejs:adv_pneumatic_machine_frame_incomplete"
        },
        {
          "item": "kubejs:lapis_tube"
        }
      ],
      "results": [
        {
          "item": "kubejs:adv_pneumatic_machine_frame_incomplete"
        }
      ]
    },
    {
      "type": "create:deploying",
      "ingredients": [
        {
          "item": "kubejs:adv_pneumatic_machine_frame_incomplete"
        },
        {
          "item": "pneumaticcraft:advanced_pressure_tube"
        }
      ],
      "results": [
        {
          "item": "kubejs:adv_pneumatic_machine_frame_incomplete"
        }
      ]
    },
    {
      "type": "create:pressing",
      "ingredients": [
        {
          "item": "kubejs:adv_pneumatic_machine_frame_incomplete"
        }
      ],
      "results": [
        {
          "item": "kubejs:adv_pneumatic_machine_frame_incomplete"
        }
      ]
    }
  ],
  "results": [
    {
      "item": "kubejs:adv_pneumatic_machine_frame"
    }
  ],
  "loops": 1
}